lucid/__init__.py
lucid/misc/__init__.py
lucid/misc/channel_reducer.py
lucid/misc/convert_matplotlib.py
lucid/misc/environment.py
lucid/misc/gradient_override.py
lucid/misc/iter_nd_utils.py
lucid/misc/ndimage_utils.py
lucid/misc/redirected_relu_grad.py
lucid/misc/stimuli.py
lucid/misc/tfutil.py
lucid/misc/gl/__init__.py
lucid/misc/gl/glcontext.py
lucid/misc/gl/glrenderer.py
lucid/misc/gl/meshutil.py
lucid/misc/graph_analysis/__init__.py
lucid/misc/graph_analysis/filter_overlay.py
lucid/misc/graph_analysis/overlay_graph.py
lucid/misc/graph_analysis/parse_overlay.py
lucid/misc/graph_analysis/property_inference.py
lucid/misc/io/__init__.py
lucid/misc/io/collapse_channels.py
lucid/misc/io/loading.py
lucid/misc/io/reading.py
lucid/misc/io/sanitizing.py
lucid/misc/io/saving.py
lucid/misc/io/scoping.py
lucid/misc/io/serialize_array.py
lucid/misc/io/showing.py
lucid/misc/io/writing.py
lucid/modelzoo/__init__.py
lucid/modelzoo/aligned_activations.py
lucid/modelzoo/get_activations.py
lucid/modelzoo/nets_factory.py
lucid/modelzoo/util.py
lucid/modelzoo/vision_base.py
lucid/modelzoo/vision_models.py
lucid/modelzoo/wordnet.py
lucid/modelzoo/caffe_models/AlexNet.py
lucid/modelzoo/caffe_models/InceptionV1.py
lucid/modelzoo/caffe_models/__init__.py
lucid/modelzoo/caffe_models/others.py
lucid/modelzoo/other_models/AlexNet.py
lucid/modelzoo/other_models/InceptionV1.py
lucid/modelzoo/other_models/__init__.py
lucid/modelzoo/slim_models/Inception.py
lucid/modelzoo/slim_models/MobilenetV1.py
lucid/modelzoo/slim_models/MobilenetV2.py
lucid/modelzoo/slim_models/ResNetV1.py
lucid/modelzoo/slim_models/ResNetV2.py
lucid/modelzoo/slim_models/__init__.py
lucid/modelzoo/slim_models/others.py
lucid/optvis/__init__.py
lucid/optvis/objectives.py
lucid/optvis/objectives_util.py
lucid/optvis/render.py
lucid/optvis/style.py
lucid/optvis/transform.py
lucid/optvis/overrides/__init__.py
lucid/optvis/overrides/gradient_override.py
lucid/optvis/overrides/identity_grad.py
lucid2-0.4.0.dist-info/LICENSE
lucid2-0.4.0.dist-info/METADATA
lucid2-0.4.0.dist-info/WHEEL
lucid2-0.4.0.dist-info/top_level.txt
lucid2-0.4.0.dist-info/RECORD
